.travis.yml
LICENSE
MANIFEST.in
README.rst
dev-requirements.txt
setup.cfg
setup.py
tox.ini
examples/genres.py
examples/new_releases.py
examples/playlists.py
examples/set_config.py
tests/__init__.py
tests/test_api.py
tests/test_cache.py
tests/test_genre.py
tests/test_playlist.py
tests/test_release.py
tests/test_translator.py
tests/test_utils.py
tunigo/__init__.py
tunigo/api.py
tunigo/cache.py
tunigo/genre.py
tunigo/playlist.py
tunigo/release.py
tunigo/translator.py
tunigo/utils.py
tunigo.egg-info/PKG-INFO
tunigo.egg-info/SOURCES.txt
tunigo.egg-info/dependency_links.txt
tunigo.egg-info/not-zip-safe
tunigo.egg-info/requires.txt
tunigo.egg-info/top_level.txt